Metadata-Version: 1.0
Name: siesta
Version: 0.3
Summary: Sit back, relax and enjoy of your python REST client
Home-page: http://scastillo.github.com/siesta/
Author: Sebastián Castillo Builes
Author-email: castillobuiles@gmail.com
License: GPL
Keywords: REST RESTful API HTTP web service
Platform: UNKNOWN
Classifier: Development Status :: 4 - Beta
Classifier: Intended Audience :: Developers
Classifier: License :: OSI Approved :: GNU General Public License (GPL)
